odoo/addons/product_packaging_dimension/README.rst
odoo/addons/product_packaging_dimension/__init__.py
odoo/addons/product_packaging_dimension/__manifest__.py
odoo/addons/product_packaging_dimension/i18n/ca.po
odoo/addons/product_packaging_dimension/i18n/es.po
odoo/addons/product_packaging_dimension/i18n/it.po
odoo/addons/product_packaging_dimension/i18n/product_packaging_dimension.pot
odoo/addons/product_packaging_dimension/models/__init__.py
odoo/addons/product_packaging_dimension/models/product_packaging.py
odoo/addons/product_packaging_dimension/readme/CONTRIBUTORS.rst
odoo/addons/product_packaging_dimension/readme/DESCRIPTION.rst
odoo/addons/product_packaging_dimension/readme/ROADMAP.rst
odoo/addons/product_packaging_dimension/static/description/icon.png
odoo/addons/product_packaging_dimension/static/description/index.html
odoo/addons/product_packaging_dimension/views/product_packaging.xml
odoo13_addon_product_packaging_dimension-13.0.1.0.1.dev11.dist-info/METADATA
odoo13_addon_product_packaging_dimension-13.0.1.0.1.dev11.dist-info/WHEEL
odoo13_addon_product_packaging_dimension-13.0.1.0.1.dev11.dist-info/top_level.txt
odoo13_addon_product_packaging_dimension-13.0.1.0.1.dev11.dist-info/RECORD
